easyaerospike/__init__.py
easyaerospike/easyaerospike.py
easyaerospike-0.0.1b0.dist-info/LICENSE
easyaerospike-0.0.1b0.dist-info/METADATA
easyaerospike-0.0.1b0.dist-info/WHEEL
easyaerospike-0.0.1b0.dist-info/top_level.txt
easyaerospike-0.0.1b0.dist-info/RECORD
